textverified_async_keynet/__init__.py
textverified_async_keynet/api.py
textverified_async_keynet/models.py
textverified_async_keynet-0.0.3.dist-info/licenses/LICENSE
textverified_async_keynet-0.0.3.dist-info/METADATA
textverified_async_keynet-0.0.3.dist-info/WHEEL
textverified_async_keynet-0.0.3.dist-info/top_level.txt
textverified_async_keynet-0.0.3.dist-info/RECORD
