Metadata-Version: 2.4
Name: textverified_async_keynet
Version: 0.0.3
Summary: A simple asynchronous Python API client for working with the Textverified REST API
Author-email: keynet <viktorplay377@gmail.com>
License-Expression: MIT
Project-URL: Homepage, https://github.com/Keynet123/textverified_async
Project-URL: Issues, https://github.com/Keynet123/textverified_async/issues
Classifier: Programming Language :: Python :: 3.10
Classifier: Operating System :: OS Independent
Requires-Python: >=3.9
License-File: LICENSE
Dynamic: license-file
